CHANGES.txt
LICENSE
MANIFEST.in
README.rst
setup.py
LICENSES/NUMPY_LICENSE
LICENSES/SIX_LICENSE
py_stringmatching/__init__.py
py_stringmatching/utils.py
py_stringmatching.egg-info/PKG-INFO
py_stringmatching.egg-info/SOURCES.txt
py_stringmatching.egg-info/dependency_links.txt
py_stringmatching.egg-info/not-zip-safe
py_stringmatching.egg-info/requires.txt
py_stringmatching.egg-info/top_level.txt
py_stringmatching/similarity_measure/__init__.py
py_stringmatching/similarity_measure/affine.py
py_stringmatching/similarity_measure/bag_distance.py
py_stringmatching/similarity_measure/cosine.py
py_stringmatching/similarity_measure/dice.py
py_stringmatching/similarity_measure/editex.py
py_stringmatching/similarity_measure/generalized_jaccard.py
py_stringmatching/similarity_measure/hamming_distance.py
py_stringmatching/similarity_measure/hybrid_similarity_measure.py
py_stringmatching/similarity_measure/jaccard.py
py_stringmatching/similarity_measure/jaro.py
py_stringmatching/similarity_measure/jaro_winkler.py
py_stringmatching/similarity_measure/levenshtein.py
py_stringmatching/similarity_measure/monge_elkan.py
py_stringmatching/similarity_measure/needleman_wunsch.py
py_stringmatching/similarity_measure/overlap_coefficient.py
py_stringmatching/similarity_measure/partial_ratio.py
py_stringmatching/similarity_measure/partial_token_sort.py
py_stringmatching/similarity_measure/phonetic_similarity_measure.py
py_stringmatching/similarity_measure/ratio.py
py_stringmatching/similarity_measure/sequence_similarity_measure.py
py_stringmatching/similarity_measure/similarity_measure.py
py_stringmatching/similarity_measure/smith_waterman.py
py_stringmatching/similarity_measure/soft_tfidf.py
py_stringmatching/similarity_measure/soundex.py
py_stringmatching/similarity_measure/tfidf.py
py_stringmatching/similarity_measure/token_similarity_measure.py
py_stringmatching/similarity_measure/token_sort.py
py_stringmatching/similarity_measure/tversky_index.py
py_stringmatching/similarity_measure/cython/__init__.py
py_stringmatching/similarity_measure/cython/cython_affine.c
py_stringmatching/similarity_measure/cython/cython_jaro.c
py_stringmatching/similarity_measure/cython/cython_jaro_winkler.c
